<?xml version="1.0" encoding="utf-8" ?>
<dwsync>
<file name="e_j_24_01.html" local="132202797926230922" remote="132203676600000000" testing="0" />
<file name="e_j_24_02.html" local="132151696223716943" remote="132203676600000000" testing="0" />
<file name="e_j_24_03.html" local="132149794083031949" remote="132203676600000000" testing="0" />
<file name="e_j_24_04.html" local="132149794083141947" remote="132203676600000000" testing="0" />
<file name="e_j_24_05.html" local="132204434938643918" remote="132204433200000000" testing="0" />
<file name="e_j_24_06.html" local="132151696223906941" remote="132203676600000000" testing="0" />
<file name="e_j_24_07.html" local="132149794084091948" remote="132203676600000000" testing="0" />
<file name="e_j_24_08.html" local="132151696224086978" remote="132203676600000000" testing="0" />
<file name="e_j_24_09.html" local="132149794084691954" remote="132203676600000000" testing="0" />
<file name="e_j_24_10.html" local="132151696224276941" remote="132203676600000000" testing="0" />
<file name="e_j_24_11.html" local="132149794085141949" remote="132203676600000000" testing="0" />
<file name="e_j_24_12.html" local="132149794085661952" remote="132203676600000000" testing="0" />
<file name="e_j_24_13.html" local="132151696224446941" remote="132203676600000000" testing="0" />
<file name="e_j_24_14.html" local="132151696224566934" remote="132203676600000000" testing="0" />
<file name="e_j_24_15.html" local="132149794086411963" remote="132203676600000000" testing="0" />
<file name="e_j_24_16.html" local="132151696224736940" remote="132203676600000000" testing="0" />
<file name="e_j_24_17.html" local="132151696224876941" remote="132203676600000000" testing="0" />
<file name="e_j_24_18.html" local="132149794087151961" remote="132203676600000000" testing="0" />
<file name="e_j_24_19.html" local="132204437080193911" remote="132204435600000000" testing="0" />
<file name="e_j_24_20.html" local="132203688969573766" remote="132204427800000000" testing="0" />
<file name="e_j_24_21.html" local="132149794087801950" remote="132203676600000000" testing="0" />
<file name="e_j_24_22.html" local="132149794087931945" remote="132203676600000000" testing="0" />
<file name="e_j_24_23.html" local="132149794088061953" remote="132203676600000000" testing="0" />
<file name="e_j_24_24.html" local="132151696225186940" remote="132203676600000000" testing="0" />
<file name="e_j_24_25.html" local="132151696225356952" remote="132203676600000000" testing="0" />
<file name="e_j_24_26.html" local="132149794089181956" remote="132203676600000000" testing="0" />
<file name="e_j_24_27.html" local="132149794089311968" remote="132203676600000000" testing="0" />
<file name="e_j_24_28.html" local="132149794089541947" remote="132203676600000000" testing="0" />
<file name="e_j_24_29.html" local="132149794090111950" remote="132203676600000000" testing="0" />
<file name="e_j_24_30.html" local="132149815120941949" remote="132203676600000000" testing="0" />
<file name="e_j_24_31.html" local="132203531795255857" remote="132203676600000000" testing="0" />
<file name="e_j_24_32.html" local="132151696225636944" remote="132203676600000000" testing="0" />
<file name="e_j_24_33.html" local="132151696225776940" remote="132203676600000000" testing="0" />
<file name="e_j_24_34.html" local="132151696225876953" remote="132203676600000000" testing="0" />
<file name="e_j_24_35.html" local="132151696225976963" remote="132203676600000000" testing="0" />
<file name="e_j_24_36.html" local="132151696226116946" remote="132203676600000000" testing="0" />
<file name="e_j_24_37.html" local="132149794093151955" remote="132203676600000000" testing="0" />
<file name="e_j_24_38.html" local="132149794093721948" remote="132203676600000000" testing="0" />
<file name="e_j_24_39.html" local="132149794094241968" remote="132203676600000000" testing="0" />
<file name="e_j_24_40.html" local="132151696226246940" remote="132203676600000000" testing="0" />
<file name="q_j_24_01.html" local="132150984878851311" remote="132203676600000000" testing="0" />
<file name="q_j_24_02.html" local="132150984879131320" remote="132203676600000000" testing="0" />
<file name="q_j_24_03.html" local="132150984879291304" remote="132203676600000000" testing="0" />
<file name="q_j_24_04.html" local="132150984879551304" remote="132203676600000000" testing="0" />
<file name="q_j_24_05.html" local="132150984879711311" remote="132203676600000000" testing="0" />
<file name="q_j_24_06.html" local="132150984879991305" remote="132203676600000000" testing="0" />
<file name="q_j_24_07.html" local="132150984880151310" remote="132203676600000000" testing="0" />
<file name="q_j_24_08.html" local="132150984880381304" remote="132203676600000000" testing="0" />
<file name="q_j_24_09.html" local="132150984880611302" remote="132203676600000000" testing="0" />
<file name="q_j_24_10.html" local="132150984880881306" remote="132203676600000000" testing="0" />
<file name="q_j_24_11.html" local="132150984881081301" remote="132203676600000000" testing="0" />
<file name="q_j_24_12.html" local="132150984881291316" remote="132203676600000000" testing="0" />
<file name="q_j_24_13.html" local="132150984881491308" remote="132203676600000000" testing="0" />
<file name="q_j_24_14.html" local="132150984881661317" remote="132203676600000000" testing="0" />
<file name="q_j_24_15.html" local="132150984881841312" remote="132203676600000000" testing="0" />
<file name="q_j_24_16.html" local="132150984882221308" remote="132203676600000000" testing="0" />
<file name="q_j_24_17.html" local="132150984882621313" remote="132203676600000000" testing="0" />
<file name="q_j_24_18.html" local="132150984883021310" remote="132203676600000000" testing="0" />
<file name="q_j_24_19.html" local="132150984883231307" remote="132203676600000000" testing="0" />
<file name="q_j_24_20.html" local="132150984883441305" remote="132203676600000000" testing="0" />
<file name="q_j_24_21.html" local="132150984883661323" remote="132203676600000000" testing="0" />
<file name="q_j_24_22.html" local="132150984883831308" remote="132203676600000000" testing="0" />
<file name="q_j_24_23.html" local="132150984884031306" remote="132203676600000000" testing="0" />
<file name="q_j_24_24.html" local="132150984884251309" remote="132203676600000000" testing="0" />
<file name="q_j_24_25.html" local="132150984884411307" remote="132203676600000000" testing="0" />
<file name="q_j_24_26.html" local="132150984884651306" remote="132203676600000000" testing="0" />
<file name="q_j_24_27.html" local="132150984884811311" remote="132203676600000000" testing="0" />
<file name="q_j_24_28.html" local="132150984885041305" remote="132203676600000000" testing="0" />
<file name="q_j_24_29.html" local="132150984885211321" remote="132203676600000000" testing="0" />
<file name="q_j_24_30.html" local="132150984885441304" remote="132203676600000000" testing="0" />
<file name="q_j_24_31.html" local="132150984885651301" remote="132203676600000000" testing="0" />
<file name="q_j_24_32.html" local="132150984885861309" remote="132203676600000000" testing="0" />
<file name="q_j_24_33.html" local="132150984886081310" remote="132203676600000000" testing="0" />
<file name="q_j_24_34.html" local="132150984886301322" remote="132203676600000000" testing="0" />
<file name="q_j_24_35.html" local="132150984886561305" remote="132203676600000000" testing="0" />
<file name="q_j_24_36.html" local="132150984886711322" remote="132203676600000000" testing="0" />
<file name="q_j_24_37.html" local="132150984886981310" remote="132203676600000000" testing="0" />
<file name="q_j_24_38.html" local="132150984887231301" remote="132203676600000000" testing="0" />
<file name="q_j_24_39.html" local="132150984887441301" remote="132203676600000000" testing="0" />
<file name="q_j_24_40.html" local="132150984887711304" remote="132203676600000000" testing="0" />
</dwsync>